plottr/__init__.py
plottr/_version.py
plottr/icons.py
plottr/log.py
plottr/py.typed
plottr/analyzer/__init__.py
plottr/analyzer/base.py
plottr/analyzer/fitters/__init__.py
plottr/analyzer/fitters/experiment_functions.py
plottr/analyzer/fitters/fitter_base.py
plottr/analyzer/fitters/generic_functions.py
plottr/analyzer/others/__init__.py
plottr/analyzer/others/find_max.py
plottr/apps/__init__.py
plottr/apps/appmanager.py
plottr/apps/apprunner.py
plottr/apps/autoplot.py
plottr/apps/inspectr.py
plottr/apps/json_viewer.py
plottr/apps/monitr.py
plottr/apps/watchdog_classes.py
plottr/apps/ui/Monitr_UI.py
plottr/apps/ui/__init__.py
plottr/apps/ui/monitr.py
plottr/config/__init__.py
plottr/config/plottrcfg_main.py
plottr/data/__init__.py
plottr/data/datadict.py
plottr/data/datadict_storage.py
plottr/data/qcodes_dataset.py
plottr/gui/__init__.py
plottr/gui/data_display.py
plottr/gui/tools.py
plottr/gui/widgets.py
plottr/node/__init__.py
plottr/node/autonode.py
plottr/node/data_selector.py
plottr/node/dim_reducer.py
plottr/node/fitter.py
plottr/node/grid.py
plottr/node/histogram.py
plottr/node/node.py
plottr/node/scaleunits.py
plottr/node/tools.py
plottr/node/filter/__init__.py
plottr/node/filter/correct_offset.py
plottr/plot/__init__.py
plottr/plot/base.py
plottr/plot/mpl/__init__.py
plottr/plot/mpl/autoplot.py
plottr/plot/mpl/plotting.py
plottr/plot/mpl/widgets.py
plottr/plot/pyqtgraph/__init__.py
plottr/plot/pyqtgraph/autoplot.py
plottr/plot/pyqtgraph/plots.py
plottr/resource/gfx/2dscatter_plot.svg
plottr/resource/gfx/axes_assign.svg
plottr/resource/gfx/colormesh_plot.svg
plottr/resource/gfx/complete.svg
plottr/resource/gfx/data_columns.svg
plottr/resource/gfx/default_file_icon.svg
plottr/resource/gfx/grid.svg
plottr/resource/gfx/image_plot.svg
plottr/resource/gfx/interrupted.svg
plottr/resource/gfx/json_file_icon.svg
plottr/resource/gfx/loading_gif.gif
plottr/resource/gfx/multi_trace_plot.svg
plottr/resource/gfx/png_file_icon.svg
plottr/resource/gfx/single_trace_plot.svg
plottr-0.15.0.dist-info/licenses/LICENSE
plottr-0.15.0.dist-info/METADATA
plottr-0.15.0.dist-info/WHEEL
plottr-0.15.0.dist-info/entry_points.txt
plottr-0.15.0.dist-info/top_level.txt
plottr-0.15.0.dist-info/RECORD
