Metadata-Version: 2.4
Name: plottr
Version: 0.15.0
Summary: A tool for live plotting and processing data
Author-email: Wolfgang Pfaff <wolfgangpfff@gmail.com>
License: MIT
Project-URL: Homepage, https://github.com/toolsforexperiments/plottr
Project-URL: Documentation, https://plottr.readthedocs.io
Project-URL: Source, https://github.com/toolsforexperiments/plottr/
Project-URL: Tracker, https://github.com/toolsforexperiments/plottr/issues
Classifier: Development Status :: 3 - Alpha
Classifier: Intended Audience :: Science/Research
Classifier: License :: OSI Approved :: MIT License
Classifier: Programming Language :: Python :: 3 :: Only
Classifier: Programming Language :: Python :: 3.10
Classifier: Programming Language :: Python :: 3.11
Classifier: Programming Language :: Python :: 3.12
Classifier: Programming Language :: Python :: 3.13
Classifier: Topic :: Scientific/Engineering
Requires-Python: >=3.10
License-File: LICENSE
Requires-Dist: pandas>=0.22
Requires-Dist: xarray
Requires-Dist: pyqtgraph>=0.12.1
Requires-Dist: matplotlib>=3.0.0
Requires-Dist: numpy>=1.12.0
Requires-Dist: lmfit>=1.0
Requires-Dist: h5py>=2.10.0
Requires-Dist: qtpy>=1.9.0
Requires-Dist: typing-extensions>=3.7.4.3
Requires-Dist: packaging>=20.0
Requires-Dist: xhistogram>=0.3.0
Requires-Dist: versioningit>=1.1.0
Requires-Dist: psutil
Requires-Dist: watchdog
Requires-Dist: pyzmq
Provides-Extra: pyqt5
Requires-Dist: PyQt5; extra == "pyqt5"
Provides-Extra: pyqt6
Requires-Dist: PyQt6; extra == "pyqt6"
Provides-Extra: pyside2
Requires-Dist: PySide2>=5.12; extra == "pyside2"
Provides-Extra: qcodes
Requires-Dist: qcodes>=0.54.1; extra == "qcodes"
Dynamic: license-file
